Workbook

Sheet About
A1: About this workbook
A3: Data source | B3: U.S. Small Business Administration, 7(a) FOIA loan data, FY2020 to present, as of June 30, 2026. https://data.sba.gov/dataset/7a-504-foia (public domain).
A4: What is a 7(a) loan? | B4: SBA's main small business loan program. Private lenders make the loans and SBA guarantees part of each one.
A5: Cleaning | B5: Cancelled loans (approved but never funded) were removed: 50,104 of 388,338 rows. Borrower names and addresses were dropped.
A6: Fiscal year | B6: SBA fiscal years run October 1 to September 30. FY2026 is partial (through June 30, 2026).
A7: Average rate | B7: Simple average of each loan's initial interest rate, not weighted by loan size.
A8: Summary | B8: Year and industry totals, built with SUMIFS formulas over the Data sheet.
A9: State Explorer | B9: Choose any state in the yellow cell to see its totals, trend, and industry mix.
A10: Virginia Loans | B10: Every funded Virginia loan, ready for filtering or a PivotTable (Insert > PivotTable).
A11: Data | B11: Aggregated by fiscal year, state, and industry sector. All other sheets calculate from it.
A12: Color code | B12: Yellow fill with blue text marks the one input cell. Everything else is a formula or source data.

Sheet Summary
A1: SBA 7(a) Small Business Lending, FY2020 to June 2026
A2: All figures calculate from the Data sheet with SUMIFS. FY2026 is a partial year (October 2025 to June 2026).
A4: Lending by fiscal year
A5: Fiscal Year | B5: Loans | C5: Total Approved ($) | D5: Avg Loan ($) | E5: Avg Rate (%) | F5: YoY Change in $
A6: 2020 | B6: =SUMIFS(Data!$D$5:$D$6318,Data!$A$5:$A$6318,G6) -> 36490 | C6: =SUMIFS(Data!$E$5:$E$6318,Data!$A$5:$A$6318,G6) -> 19508718600 | D6: =IFERROR(C6/B6,0) -> 534631.92 | E6: =IFERROR(SUMIFS(Data!$F$5:$F$6318,Data!$A$5:$A$6318,G6)/B6,0) -> 6.4573729 | G6: 2020
A7: 2021 | B7: =SUMIFS(Data!$D$5:$D$6318,Data!$A$5:$A$6318,G7) -> 45360 | C7: =SUMIFS(Data!$E$5:$E$6318,Data!$A$5:$A$6318,G7) -> 32203041400 | D7: =IFERROR(C7/B7,0) -> 709943.59 | E7: =IFERROR(SUMIFS(Data!$F$5:$F$6318,Data!$A$5:$A$6318,G7)/B7,0) -> 5.4865397 | F7: =IFERROR(C7/C6-1,0) -> 0.65069998 | G7: 2021
A8: 2022 | B8: =SUMIFS(Data!$D$5:$D$6318,Data!$A$5:$A$6318,G8) -> 42282 | C8: =SUMIFS(Data!$E$5:$E$6318,Data!$A$5:$A$6318,G8) -> 23269324000 | D8: =IFERROR(C8/B8,0) -> 550336.41 | E8: =IFERROR(SUMIFS(Data!$F$5:$F$6318,Data!$A$5:$A$6318,G8)/B8,0) -> 6.4174895 | F8: =IFERROR(C8/C7-1,0) -> -0.27741844 | G8: 2022
A9: 2023 | B9: =SUMIFS(Data!$D$5:$D$6318,Data!$A$5:$A$6318,G9) -> 51747 | C9: =SUMIFS(Data!$E$5:$E$6318,Data!$A$5:$A$6318,G9) -> 24655068800 | D9: =IFERROR(C9/B9,0) -> 476454.07 | E9: =IFERROR(SUMIFS(Data!$F$5:$F$6318,Data!$A$5:$A$6318,G9)/B9,0) -> 10.124077 | F9: =IFERROR(C9/C8-1,0) -> 0.05955243 | G9: 2023
A10: 2024 | B10: =SUMIFS(Data!$D$5:$D$6318,Data!$A$5:$A$6318,G10) -> 62618 | C10: =SUMIFS(Data!$E$5:$E$6318,Data!$A$5:$A$6318,G10) -> 27517974500 | D10: =IFERROR(C10/B10,0) -> 439457.9 | E10: =IFERROR(SUMIFS(Data!$F$5:$F$6318,Data!$A$5:$A$6318,G10)/B10,0) -> 11.110468 | F10: =IFERROR(C10/C9-1,0) -> 0.11611834 | G10: 2024
A11: 2025 | B11: =SUMIFS(Data!$D$5:$D$6318,Data!$A$5:$A$6318,G11) -> 64096 | C11: =SUMIFS(Data!$E$5:$E$6318,Data!$A$5:$A$6318,G11) -> 32065939300 | D11: =IFERROR(C11/B11,0) -> 500279.88 | E11: =IFERROR(SUMIFS(Data!$F$5:$F$6318,Data!$A$5:$A$6318,G11)/B11,0) -> 10.235936 | F11: =IFERROR(C11/C10-1,0) -> 0.16527251 | G11: 2025
A12: 2026* | B12: =SUMIFS(Data!$D$5:$D$6318,Data!$A$5:$A$6318,G12) -> 35641 | C12: =SUMIFS(Data!$E$5:$E$6318,Data!$A$5:$A$6318,G12) -> 19885185218 | D12: =IFERROR(C12/B12,0) -> 557930.06 | E12: =IFERROR(SUMIFS(Data!$F$5:$F$6318,Data!$A$5:$A$6318,G12)/B12,0) -> 9.4973851 | F12: n/a (partial year) | G12: 2026
A13: Total | B13: =SUM(B6:B12) -> 338234 | C13: =SUM(C6:C12) -> 179105251818 | D13: =IFERROR(C13/B13,0) -> 529530.6
A16: Lending by industry sector (all years)
A17: Industry Sector | B17: Loans | C17: Total Approved ($) | D17: Avg Loan ($) | E17: Share of $
A18: Accommodation & Food Services | B18: =SUMIFS(Data!$D$5:$D$6318,Data!$C$5:$C$6318,A18) -> 42538 | C18: =SUMIFS(Data!$E$5:$E$6318,Data!$C$5:$C$6318,A18) -> 31450885300 | D18: =IFERROR(C18/B18,0) -> 739359.76 | E18: =IFERROR(C18/$C$13,0) -> 0.17560002
A19: Retail Trade | B19: =SUMIFS(Data!$D$5:$D$6318,Data!$C$5:$C$6318,A19) -> 41250 | C19: =SUMIFS(Data!$E$5:$E$6318,Data!$C$5:$C$6318,A19) -> 24800871000 | D19: =IFERROR(C19/B19,0) -> 601233.24 | E19: =IFERROR(C19/$C$13,0) -> 0.13847093
A20: Health Care & Social Assistance | B20: =SUMIFS(Data!$D$5:$D$6318,Data!$C$5:$C$6318,A20) -> 32313 | C20: =SUMIFS(Data!$E$5:$E$6318,Data!$C$5:$C$6318,A20) -> 19691369500 | D20: =IFERROR(C20/B20,0) -> 609394.66 | E20: =IFERROR(C20/$C$13,0) -> 0.109943
A21: Construction | B21: =SUMIFS(Data!$D$5:$D$6318,Data!$C$5:$C$6318,A21) -> 43592 | C21: =SUMIFS(Data!$E$5:$E$6318,Data!$C$5:$C$6318,A21) -> 16220011300 | D21: =IFERROR(C21/B21,0) -> 372086.88 | E21: =IFERROR(C21/$C$13,0) -> 0.090561338
A22: Other Services | B22: =SUMIFS(Data!$D$5:$D$6318,Data!$C$5:$C$6318,A22) -> 32351 | C22: =SUMIFS(Data!$E$5:$E$6318,Data!$C$5:$C$6318,A22) -> 14998889018 | D22: =IFERROR(C22/B22,0) -> 463629.84 | E22: =IFERROR(C22/$C$13,0) -> 0.083743435
A23: Manufacturing | B23: =SUMIFS(Data!$D$5:$D$6318,Data!$C$5:$C$6318,A23) -> 20997 | C23: =SUMIFS(Data!$E$5:$E$6318,Data!$C$5:$C$6318,A23) -> 14227067600 | D23: =IFERROR(C23/B23,0) -> 677576.21 | E23: =IFERROR(C23/$C$13,0) -> 0.079434117
A24: Professional & Technical Services | B24: =SUMIFS(Data!$D$5:$D$6318,Data!$C$5:$C$6318,A24) -> 31918 | C24: =SUMIFS(Data!$E$5:$E$6318,Data!$C$5:$C$6318,A24) -> 13635612500 | D24: =IFERROR(C24/B24,0) -> 427207.61 | E24: =IFERROR(C24/$C$13,0) -> 0.076131841
A25: Wholesale Trade | B25: =SUMIFS(Data!$D$5:$D$6318,Data!$C$5:$C$6318,A25) -> 14394 | C25: =SUMIFS(Data!$E$5:$E$6318,Data!$C$5:$C$6318,A25) -> 9569860000 | D25: =IFERROR(C25/B25,0) -> 664850.63 | E25: =IFERROR(C25/$C$13,0) -> 0.053431487
A26: Admin, Support & Waste Services | B26: =SUMIFS(Data!$D$5:$D$6318,Data!$C$5:$C$6318,A26) -> 19634 | C26: =SUMIFS(Data!$E$5:$E$6318,Data!$C$5:$C$6318,A26) -> 6996470000 | D26: =IFERROR(C26/B26,0) -> 356344.61 | E26: =IFERROR(C26/$C$13,0) -> 0.039063455
A27: Arts, Entertainment & Recreation | B27: =SUMIFS(Data!$D$5:$D$6318,Data!$C$5:$C$6318,A27) -> 12060 | C27: =SUMIFS(Data!$E$5:$E$6318,Data!$C$5:$C$6318,A27) -> 6133117600 | D27: =IFERROR(C27/B27,0) -> 508550.38 | E27: =IFERROR(C27/$C$13,0) -> 0.034243092
A28: Transportation & Warehousing | B28: =SUMIFS(Data!$D$5:$D$6318,Data!$C$5:$C$6318,A28) -> 19461 | C28: =SUMIFS(Data!$E$5:$E$6318,Data!$C$5:$C$6318,A28) -> 6049758200 | D28: =IFERROR(C28/B28,0) -> 310865.74 | E28: =IFERROR(C28/$C$13,0) -> 0.033777671
A29: Real Estate & Rental | B29: =SUMIFS(Data!$D$5:$D$6318,Data!$C$5:$C$6318,A29) -> 8096 | C29: =SUMIFS(Data!$E$5:$E$6318,Data!$C$5:$C$6318,A29) -> 4947225400 | D29: =IFERROR(C29/B29,0) -> 611070.33 | E29: =IFERROR(C29/$C$13,0) -> 0.027621889
... A37: Public Administration | B37: =SUMIFS(Data!$D$5:$D$6318,Data!$C$5:$C$6318,A37) -> 93 | C37: =SUMIFS(Data!$E$5:$E$6318,Data!$C$5:$C$6318,A37) -> 30365600 | D37: =IFERROR(C37/B37,0) -> 326511.83 | E37: =IFERROR(C37/$C$13,0) -> 0.00016954053
A39: * FY2026 covers October 2025 to June 30, 2026 only, so it is not comparable to full years.

Sheet State Explorer
A1: State Explorer
A2: Pick a state in the yellow cell. Every number below recalculates from the Data sheet.
A4: State (2-letter code): | B4: VA
A6: Total loans | B6: =SUMIFS(Data!$D$5:$D$6318,Data!$B$5:$B$6318,$B$4) -> 5686
A7: Total approved ($) | B7: =SUMIFS(Data!$E$5:$E$6318,Data!$B$5:$B$6318,$B$4) -> 3137483900
A8: Average loan ($) | B8: =IFERROR(B7/B6,0) -> 551791.05
A9: Average interest rate (%) | B9: =IFERROR(SUMIFS(Data!$F$5:$F$6318,Data!$B$5:$B$6318,$B$4)/B6,0) -> 9.1660375
A10: Share of national dollars | B10: =IFERROR(B7/SUM(Data!$E$5:$E$6318),0) -> 0.017517543
A11: National rank by dollars | B11: =IFERROR(MATCH($B$4,Lists!$B$1:$B$54,0),"") -> 18 | C11: Rank list is precomputed in the hidden Lists sheet, sorted by total dollars.
A13: Fiscal Year | B13: Loans | C13: Total Approved ($) | D13: Avg Rate (%)
A14: 2020 | B14: =SUMIFS(Data!$D$5:$D$6318,Data!$B$5:$B$6318,$B$4,Data!$A$5:$A$6318,A14) -> 537 | C14: =SUMIFS(Data!$E$5:$E$6318,Data!$B$5:$B$6318,$B$4,Data!$A$5:$A$6318,A14) -> 310274600 | D14: =IFERROR(SUMIFS(Data!$F$5:$F$6318,Data!$B$5:$B$6318,$B$4,Data!$A$5:$A$6318,A14)/B14,0) -> 6.8086778
A15: 2021 | B15: =SUMIFS(Data!$D$5:$D$6318,Data!$B$5:$B$6318,$B$4,Data!$A$5:$A$6318,A15) -> 657 | C15: =SUMIFS(Data!$E$5:$E$6318,Data!$B$5:$B$6318,$B$4,Data!$A$5:$A$6318,A15) -> 503064500 | D15: =IFERROR(SUMIFS(Data!$F$5:$F$6318,Data!$B$5:$B$6318,$B$4,Data!$A$5:$A$6318,A15)/B15,0) -> 5.8247412
A16: 2022 | B16: =SUMIFS(Data!$D$5:$D$6318,Data!$B$5:$B$6318,$B$4,Data!$A$5:$A$6318,A16) -> 696 | C16: =SUMIFS(Data!$E$5:$E$6318,Data!$B$5:$B$6318,$B$4,Data!$A$5:$A$6318,A16) -> 391601000 | D16: =IFERROR(SUMIFS(Data!$F$5:$F$6318,Data!$B$5:$B$6318,$B$4,Data!$A$5:$A$6318,A16)/B16,0) -> 6.6996767
A17: 2023 | B17: =SUMIFS(Data!$D$5:$D$6318,Data!$B$5:$B$6318,$B$4,Data!$A$5:$A$6318,A17) -> 848 | C17: =SUMIFS(Data!$E$5:$E$6318,Data!$B$5:$B$6318,$B$4,Data!$A$5:$A$6318,A17) -> 441135100 | D17: =IFERROR(SUMIFS(Data!$F$5:$F$6318,Data!$B$5:$B$6318,$B$4,Data!$A$5:$A$6318,A17)/B17,0) -> 10.45036
A18: 2024 | B18: =SUMIFS(Data!$D$5:$D$6318,Data!$B$5:$B$6318,$B$4,Data!$A$5:$A$6318,A18) -> 1061 | C18: =SUMIFS(Data!$E$5:$E$6318,Data!$B$5:$B$6318,$B$4,Data!$A$5:$A$6318,A18) -> 483661000 | D18: =IFERROR(SUMIFS(Data!$F$5:$F$6318,Data!$B$5:$B$6318,$B$4,Data!$A$5:$A$6318,A18)/B18,0) -> 11.401027
A19: 2025 | B19: =SUMIFS(Data!$D$5:$D$6318,Data!$B$5:$B$6318,$B$4,Data!$A$5:$A$6318,A19) -> 1192 | C19: =SUMIFS(Data!$E$5:$E$6318,Data!$B$5:$B$6318,$B$4,Data!$A$5:$A$6318,A19) -> 655314200 | D19: =IFERROR(SUMIFS(Data!$F$5:$F$6318,Data!$B$5:$B$6318,$B$4,Data!$A$5:$A$6318,A19)/B19,0) -> 10.317982
A20: 2026 | B20: =SUMIFS(Data!$D$5:$D$6318,Data!$B$5:$B$6318,$B$4,Data!$A$5:$A$6318,A20) -> 695 | C20: =SUMIFS(Data!$E$5:$E$6318,Data!$B$5:$B$6318,$B$4,Data!$A$5:$A$6318,A20) -> 352433500 | D20: =IFERROR(SUMIFS(Data!$F$5:$F$6318,Data!$B$5:$B$6318,$B$4,Data!$A$5:$A$6318,A20)/B20,0) -> 9.6612518
A22: Industry Sector | B22: Loans | C22: Total Approved ($) | D22: Share of State $
A23: Accommodation & Food Services | B23: =SUMIFS(Data!$D$5:$D$6318,Data!$B$5:$B$6318,$B$4,Data!$C$5:$C$6318,A23) -> 789 | C23: =SUMIFS(Data!$E$5:$E$6318,Data!$B$5:$B$6318,$B$4,Data!$C$5:$C$6318,A23) -> 694888600 | D23: =IFERROR(C23/$B$7,0) -> 0.22147957
A24: Retail Trade | B24: =SUMIFS(Data!$D$5:$D$6318,Data!$B$5:$B$6318,$B$4,Data!$C$5:$C$6318,A24) -> 543 | C24: =SUMIFS(Data!$E$5:$E$6318,Data!$B$5:$B$6318,$B$4,Data!$C$5:$C$6318,A24) -> 256853200 | D24: =IFERROR(C24/$B$7,0) -> 0.081865982
A25: Health Care & Social Assistance | B25: =SUMIFS(Data!$D$5:$D$6318,Data!$B$5:$B$6318,$B$4,Data!$C$5:$C$6318,A25) -> 629 | C25: =SUMIFS(Data!$E$5:$E$6318,Data!$B$5:$B$6318,$B$4,Data!$C$5:$C$6318,A25) -> 386016600 | D25: =IFERROR(C25/$B$7,0) -> 0.12303381
A26: Construction | B26: =SUMIFS(Data!$D$5:$D$6318,Data!$B$5:$B$6318,$B$4,Data!$C$5:$C$6318,A26) -> 602 | C26: =SUMIFS(Data!$E$5:$E$6318,Data!$B$5:$B$6318,$B$4,Data!$C$5:$C$6318,A26) -> 264945500 | D26: =IFERROR(C26/$B$7,0) -> 0.084445214
A27: Other Services | B27: =SUMIFS(Data!$D$5:$D$6318,Data!$B$5:$B$6318,$B$4,Data!$C$5:$C$6318,A27) -> 565 | C27: =SUMIFS(Data!$E$5:$E$6318,Data!$B$5:$B$6318,$B$4,Data!$C$5:$C$6318,A27) -> 266086800 | D27: =IFERROR(C27/$B$7,0) -> 0.084808977
A28: Manufacturing | B28: =SUMIFS(Data!$D$5:$D$6318,Data!$B$5:$B$6318,$B$4,Data!$C$5:$C$6318,A28) -> 283 | C28: =SUMIFS(Data!$E$5:$E$6318,Data!$B$5:$B$6318,$B$4,Data!$C$5:$C$6318,A28) -> 178585700 | D28: =IFERROR(C28/$B$7,0) -> 0.056920037
A29: Professional & Technical Services | B29: =SUMIFS(Data!$D$5:$D$6318,Data!$B$5:$B$6318,$B$4,Data!$C$5:$C$6318,A29) -> 818 | C29: =SUMIFS(Data!$E$5:$E$6318,Data!$B$5:$B$6318,$B$4,Data!$C$5:$C$6318,A29) -> 396348600 | D29: =IFERROR(C29/$B$7,0) -> 0.1263269
A30: Wholesale Trade | B30: =SUMIFS(Data!$D$5:$D$6318,Data!$B$5:$B$6318,$B$4,Data!$C$5:$C$6318,A30) -> 164 | C30: =SUMIFS(Data!$E$5:$E$6318,Data!$B$5:$B$6318,$B$4,Data!$C$5:$C$6318,A30) -> 95656400 | D30: =IFERROR(C30/$B$7,0) -> 0.030488252
A31: Admin, Support & Waste Services | B31: =SUMIFS(Data!$D$5:$D$6318,Data!$B$5:$B$6318,$B$4,Data!$C$5:$C$6318,A31) -> 352 | C31: =SUMIFS(Data!$E$5:$E$6318,Data!$B$5:$B$6318,$B$4,Data!$C$5:$C$6318,A31) -> 117519400 | D31: =IFERROR(C31/$B$7,0) -> 0.037456575
A32: Arts, Entertainment & Recreation | B32: =SUMIFS(Data!$D$5:$D$6318,Data!$B$5:$B$6318,$B$4,Data!$C$5:$C$6318,A32) -> 273 | C32: =SUMIFS(Data!$E$5:$E$6318,Data!$B$5:$B$6318,$B$4,Data!$C$5:$C$6318,A32) -> 168973600 | D32: =IFERROR(C32/$B$7,0) -> 0.053856404
A33: Transportation & Warehousing | B33: =SUMIFS(Data!$D$5:$D$6318,Data!$B$5:$B$6318,$B$4,Data!$C$5:$C$6318,A33) -> 251 | C33: =SUMIFS(Data!$E$5:$E$6318,Data!$B$5:$B$6318,$B$4,Data!$C$5:$C$6318,A33) -> 95898000 | D33: =IFERROR(C33/$B$7,0) -> 0.030565256
A34: Real Estate & Rental | B34: =SUMIFS(Data!$D$5:$D$6318,Data!$B$5:$B$6318,$B$4,Data!$C$5:$C$6318,A34) -> 102 | C34: =SUMIFS(Data!$E$5:$E$6318,Data!$B$5:$B$6318,$B$4,Data!$C$5:$C$6318,A34) -> 51974000 | D34: =IFERROR(C34/$B$7,0) -> 0.016565503
... A42: Public Administration | B42: =SUMIFS(Data!$D$5:$D$6318,Data!$B$5:$B$6318,$B$4,Data!$C$5:$C$6318,A42) -> 3 | C42: =SUMIFS(Data!$E$5:$E$6318,Data!$B$5:$B$6318,$B$4,Data!$C$5:$C$6318,A42) -> 440000 | D42: =IFERROR(C42/$B$7,0) -> 0.00014023976

Sheet Lists
A1: AK | B1: CA
A2: AL | B2: TX
A3: AR | B3: FL
A4: AZ | B4: GA
A5: CA | B5: NY
A6: CO | B6: OH
A7: CT | B7: IL
A8: DC | B8: CO
A9: DE | B9: WA
A10: FL | B10: NC
A11: GA | B11: NJ
A12: GU | B12: PA
... A54: WY | B54: GU

Sheet Virginia Loans
A1: Virginia SBA 7(a) loans (loan level)
A2: Borrower names and addresses removed. Use the filters to explore by county, industry, or product.
A4: Approval Date | B4: Fiscal Year | C4: County / City | D4: Industry Sector | E4: NAICS Description | F4: Product | G4: Business Age | H4: Lender | I4: Loan Amount ($) | J4: SBA Guarantee ($) | K4: Interest Rate (%) | L4: Term (Months) | M4: Jobs Supported
A5: 43739 | B5: 2020 | C5: CHESAPEAKE CITY | D5: Health Care & Social Assistance | E5: Child Day Care Services | F5: Preferred Lender (PLP) | G5: Startup | H5: Live Oak Banking Company | I5: 5000000 | J5: 3750000 | K5: 6 | L5: 312 | M5: 91
A6: 43739 | B6: 2020 | C6: ARLINGTON | D6: Other Services | E6: Drycleaning and Laundry Services (except Coin-Operated) | F6: SBA Express | G6: Existing (2+ years) | H6: Hanmi Bank | I6: 22000 | J6: 11000 | K6: 9 | L6: 51 | M6: 2
A7: 43740 | B7: 2020 | C7: BOTETOURT | D7: Manufacturing | E7: Commercial Screen Printing | F7: Preferred Lender (PLP) | G7: Change of Ownership | H7: The Bancorp Bank National Association | I7: 421900 | J7: 316425 | K7: 6 | L7: 119 | M7: 2
A8: 43740 | B8: 2020 | C8: WINCHESTER CITY | D8: Finance & Insurance | E8: Investment Advice | F8: Preferred Lender (PLP) | G8: Unanswered | H8: Live Oak Banking Company | I8: 425000 | J8: 318750 | K8: 6.89 | L8: 300 | M8: 0
A9: 43740 | B9: 2020 | C9: ESSEX | D9: Agriculture, Forestry & Fishing | E9: Logging | F9: SBA Express | G9: Existing (2+ years) | H9: Manufacturers and Traders Trust Company | I9: 30000 | J9: 15000 | K9: 8.25 | L9: 60 | M9: 8
A10: 43740 | B10: 2020 | C10: HENRICO | D10: Health Care & Social Assistance | E10: Offices of Dentists | F10: Preferred Lender (PLP) | G10: Unanswered | H10: Bank of America, National Association | I10: 245500 | J10: 184125 | K10: 4.99 | L10: 300 | M10: 1
A11: 43741 | B11: 2020 | C11: VIRGINIA BEACH CITY | D11: Accommodation & Food Services | E11: Full-Service Restaurants | F11: Preferred Lender (PLP) | G11: Startup | H11: Truist Bank | I11: 123300 | J11: 104805 | K11: 5.14 | L11: 60 | M11: 24
A12: 43741 | B12: 2020 | C12: PRINCE WILLIAM | D12: Health Care & Social Assistance | E12: Home Health Care Services | F12: SBA Express | G12: Unanswered | H12: Wells Fargo Bank National Association | I12: 7500 | J12: 3750 | K12: 11.5 | L12: 120 | M12: 0
A13: 43742 | B13: 2020 | C13: LOUDOUN | D13: Professional & Technical Services | E13: Other Management Consulting Services | F13: Preferred Lender (PLP) | G13: Existing (2+ years) | H13: BayFirst National Bank | I13: 175000 | J13: 131250 | K13: 7.75 | L13: 120 | M13: 5
A14: 43742 | B14: 2020 | C14: FAIRFAX | D14: Accommodation & Food Services | E14: Full-Service Restaurants | F14: SBA Express | G14: Existing (2+ years) | H14: Manufacturers and Traders Trust Company | I14: 80000 | J14: 40000 | K14: 9.5 | L14: 55 | M14: 0
A15: 43742 | B15: 2020 | C15: PRINCE GEORGE | D15: Health Care & Social Assistance | E15: Child Day Care Services | F15: SBA Express | G15: Unanswered | H15: Wells Fargo Bank National Association | I15: 15000 | J15: 7500 | K15: 10 | L15: 120 | M15: 0
A16: 43745 | B16: 2020 | C16: FAIRFAX | D16: Admin, Support & Waste Services | E16: Office Administrative Services | F16: SBA Express | G16: Existing (2+ years) | H16: Wells Fargo Bank National Association | I16: 15000 | J16: 7500 | K16: 9.5 | L16: 120 | M16: 0
... A5690: 46203 | B5690: 2026 | C5690: BRISTOL | D5690: Construction | E5690: Plumbing, Heating, and Air-Conditioning Contractors | F5690: Preferred Lender (PLP) | G5690: Startup | H5690: Live Oak Banking Company | I5690: 275000 | J5690: 206250 | K5690: 10.24 | L5690: 120 | M5690: 3

Sheet Data
A1: Aggregated SBA 7(a) loans: fiscal year x state x industry
A2: Source: SBA 7(a) FOIA data, FY2020 to June 30, 2026 (data.sba.gov). Cancelled loans removed. Built by src/build_excel_tableau.py.
A4: Fiscal Year | B4: State | C4: Industry Sector | D4: Loans | E4: Total Approved ($) | F4: Sum of Interest Rates | G4: Avg Rate (%)
A5: 2020 | B5: AK | C5: Accommodation & Food Services | D5: 6 | E5: 3436300 | F5: 40.75 | G5: =IFERROR(F5/D5,0) -> 6.7916667
A6: 2020 | B6: AK | C6: Admin, Support & Waste Services | D6: 4 | E6: 2999500 | F6: 28.75 | G6: =IFERROR(F6/D6,0) -> 7.1875
A7: 2020 | B7: AK | C7: Agriculture, Forestry & Fishing | D7: 4 | E7: 273000 | F7: 29 | G7: =IFERROR(F7/D7,0) -> 7.25
A8: 2020 | B8: AK | C8: Arts, Entertainment & Recreation | D8: 2 | E8: 2883300 | F8: 13 | G8: =IFERROR(F8/D8,0) -> 6.5
A9: 2020 | B9: AK | C9: Construction | D9: 6 | E9: 698000 | F9: 45 | G9: =IFERROR(F9/D9,0) -> 7.5
A10: 2020 | B10: AK | C10: Educational Services | D10: 3 | E10: 230000 | F10: 21.5 | G10: =IFERROR(F10/D10,0) -> 7.1666667
A11: 2020 | B11: AK | C11: Finance & Insurance | D11: 1 | E11: 1273600 | F11: 5.25 | G11: =IFERROR(F11/D11,0) -> 5.25
A12: 2020 | B12: AK | C12: Health Care & Social Assistance | D12: 11 | E12: 2234100 | F12: 67.35 | G12: =IFERROR(F12/D12,0) -> 6.1227273
A13: 2020 | B13: AK | C13: Manufacturing | D13: 3 | E13: 1350500 | F13: 20.25 | G13: =IFERROR(F13/D13,0) -> 6.75
A14: 2020 | B14: AK | C14: Other Services | D14: 6 | E14: 4688600 | F14: 35.25 | G14: =IFERROR(F14/D14,0) -> 5.875
A15: 2020 | B15: AK | C15: Professional & Technical Services | D15: 4 | E15: 590000 | F15: 25.5 | G15: =IFERROR(F15/D15,0) -> 6.375
A16: 2020 | B16: AK | C16: Retail Trade | D16: 11 | E16: 4413000 | F16: 89.75 | G16: =IFERROR(F16/D16,0) -> 8.1590909
... A6318: 2026 | B6318: WY | C6318: Wholesale Trade | D6318: 2 | E6318: 400500 | F6318: 19.75 | G6318: =IFERROR(F6318/D6318,0) -> 9.875
